pagevalidation/__init__.py
pagevalidation/pageval.py
hospitalmproject-0.1.dist-info/METADATA
hospitalmproject-0.1.dist-info/WHEEL
hospitalmproject-0.1.dist-info/top_level.txt
hospitalmproject-0.1.dist-info/RECORD
